gateway_sdk/__init__.py
gateway_sdk/auth.py
gateway_sdk/client.py
gateway_sdk/exceptions.py
gateway_sdk/models.py
gateway_sdk/streaming.py
agent_builder_gateway_sdk-0.7.1.dist-info/METADATA
agent_builder_gateway_sdk-0.7.1.dist-info/WHEEL
agent_builder_gateway_sdk-0.7.1.dist-info/licenses/LICENSE
agent_builder_gateway_sdk-0.7.1.dist-info/RECORD
